PKG-INFO
README
README.rst
lprettytable.py
setup.cfg
setup.py
lprettytable.egg-info/PKG-INFO
lprettytable.egg-info/SOURCES.txt
lprettytable.egg-info/dependency_links.txt
lprettytable.egg-info/top_level.txt