Metadata-Version: 1.0
Name: lprettytable
Version: 0.5
Summary: A simple Python library for easily displaying tabular data in a visually appealing ASCII table format
Home-page: https://github.com/cloudnull/lprettytable
Author: Luke Maurits
Author-email: luke@maurits.id.au
License: http://www.luke.maurits.id.au/software/bsdlicense.txt
Platform: UNKNOWN
